qwc_services_core/__init__.py
qwc_services_core/api.py
qwc_services_core/app.py
qwc_services_core/auth.py
qwc_services_core/cache.py
qwc_services_core/config_models.py
qwc_services_core/database.py
qwc_services_core/jwt.py
qwc_services_core/permissions_reader.py
qwc_services_core/runtime_config.py
qwc_services_core/tenant_handler.py
qwc_services_core/translator.py
qwc_services_core-1.5.0.dist-info/licenses/LICENSE
qwc_services_core-1.5.0.dist-info/METADATA
qwc_services_core-1.5.0.dist-info/WHEEL
qwc_services_core-1.5.0.dist-info/top_level.txt
qwc_services_core-1.5.0.dist-info/RECORD
