Metadata-Version: 2.4
Name: qwc-services-core
Version: 1.5.0
Summary: Shared modules for QWC services
Home-page: https://github.com/qwc-services/qwc-services-core
Author: Sourcepole AG
Author-email: info@sourcepole.ch
Classifier: Programming Language :: Python :: 3
Classifier: License :: OSI Approved :: MIT License
Classifier: Operating System :: OS Independent
Requires-Python: >=3.5
License-File: LICENSE
Dynamic: author
Dynamic: author-email
Dynamic: classifier
Dynamic: description
Dynamic: description-content-type
Dynamic: home-page
Dynamic: license-file
Dynamic: requires-python
Dynamic: summary
